quisby/__init__.py
quisby/benchmarks/__init__.py
quisby/benchmarks/aim/__init__.py
quisby/benchmarks/aim/comparison.py
quisby/benchmarks/aim/extract.py
quisby/benchmarks/aim/graph.py
quisby/benchmarks/aim/summary.py
quisby/benchmarks/autohpl/__init__.py
quisby/benchmarks/autohpl/comparison.py
quisby/benchmarks/autohpl/extract.py
quisby/benchmarks/autohpl/graph.py
quisby/benchmarks/autohpl/summary.py
quisby/benchmarks/etcd/__init__.py
quisby/benchmarks/etcd/etcd.py
quisby/benchmarks/fio/__init__.py
quisby/benchmarks/fio/comparison.py
quisby/benchmarks/fio/fio.py
quisby/benchmarks/fio/graph.py
quisby/benchmarks/fio/summary.py
quisby/benchmarks/hammerdb/__init__.py
quisby/benchmarks/hammerdb/comparison.py
quisby/benchmarks/hammerdb/extract.py
quisby/benchmarks/hammerdb/graph.py
quisby/benchmarks/hammerdb/summary.py
quisby/benchmarks/linpack/__init__.py
quisby/benchmarks/linpack/comparison.py
quisby/benchmarks/linpack/extract.py
quisby/benchmarks/linpack/graph.py
quisby/benchmarks/linpack/summary.py
quisby/benchmarks/pig/__init__.py
quisby/benchmarks/pig/comparison.py
quisby/benchmarks/pig/extract.py
quisby/benchmarks/pig/graph.py
quisby/benchmarks/pig/summary.py
quisby/benchmarks/reboot/__init__.py
quisby/benchmarks/reboot/graph.py
quisby/benchmarks/reboot/reboot.py
quisby/benchmarks/reboot/summary.py
quisby/benchmarks/speccpu/__init__.py
quisby/benchmarks/speccpu/comparison.py
quisby/benchmarks/speccpu/extract.py
quisby/benchmarks/speccpu/graph.py
quisby/benchmarks/speccpu/summary.py
quisby/benchmarks/specjbb/__init__.py
quisby/benchmarks/specjbb/comparison.py
quisby/benchmarks/specjbb/graph.py
quisby/benchmarks/specjbb/specjbb.py
quisby/benchmarks/streams/__init__.py
quisby/benchmarks/streams/comparison.py
quisby/benchmarks/streams/graph.py
quisby/benchmarks/streams/streams.py
quisby/benchmarks/uperf/__init__.py
quisby/benchmarks/uperf/comparison.py
quisby/benchmarks/uperf/graph.py
quisby/benchmarks/uperf/uperf.py
quisby/config.py
quisby/credentials/__init__.py
quisby-0.2.dist-info/entry_points.txt
quisby-0.2.dist-info/LICENSE
quisby-0.2.dist-info/WHEEL
quisby-0.2.dist-info/METADATA
quisby-0.2.dist-info/RECORD
