Metadata-Version: 2.1
Name: quisby
Version: 0.2
Summary: Quisby is a tool to provide first view into the results from various benchmarks such as linpack, streams, fio etc.
Home-page: https://github.com/sourabhtk37/Quisby
Author: T K Sourab
Author-email: tsourab@redhat.com
Requires-Python: >=3.9,<4.0
Classifier: Programming Language :: Python :: 3
Classifier: Programming Language :: Python :: 3.9
Requires-Dist: boto3 (>=1.17.97,<2.0.0)
Requires-Dist: bs4 (>=0.0.1,<0.0.2)
Requires-Dist: google-api-core (>=1.30.0,<2.0.0)
Requires-Dist: google-api-python-client (>=2.9.0,<3.0.0)
Requires-Dist: google-auth-oauthlib (>=0.4.4,<0.5.0)
Requires-Dist: google_api (>=0.1.12,<0.2.0)
